multiplexermanager/__init__.py
multiplexermanager/fileopener.py
multiplexermanager/operations.py
multiplexermanager/plotting.py
multiplexer_manager-1.2.1.dist-info/LICENSE
multiplexer_manager-1.2.1.dist-info/METADATA
multiplexer_manager-1.2.1.dist-info/WHEEL
multiplexer_manager-1.2.1.dist-info/top_level.txt
multiplexer_manager-1.2.1.dist-info/RECORD
